adslproxy/__init__.py
adslproxy/__version__.py
adslproxy/cmd.py
adslproxy/db.py
adslproxy/settings.py
adslproxy/checker/__init__.py
adslproxy/checker/checker.py
adslproxy/sender/__init__.py
adslproxy/sender/loop.py
adslproxy/sender/sender.py
adslproxy/server/__init__.py
adslproxy/server/server.py
adslproxy-3.0.3.dist-info/LICENSE
adslproxy-3.0.3.dist-info/METADATA
adslproxy-3.0.3.dist-info/WHEEL
adslproxy-3.0.3.dist-info/entry_points.txt
adslproxy-3.0.3.dist-info/top_level.txt
adslproxy-3.0.3.dist-info/RECORD
